neurodynex3/__init__.py
neurodynex3/adex_model/AdEx.py
neurodynex3/adex_model/__init__.py
neurodynex3/brunel_model/LIF_spiking_network.py
neurodynex3/brunel_model/__init__.py
neurodynex3/cable_equation/__init__.py
neurodynex3/cable_equation/passive_cable.py
neurodynex3/competing_populations/__init__.py
neurodynex3/competing_populations/decision_making.py
neurodynex3/data/alphabet.pickle.gz
neurodynex3/exponential_integrate_fire/__init__.py
neurodynex3/exponential_integrate_fire/exp_IF.py
neurodynex3/hodgkin_huxley/HH.py
neurodynex3/hodgkin_huxley/__init__.py
neurodynex3/hopfield_network/__init__.py
neurodynex3/hopfield_network/demo.py
neurodynex3/hopfield_network/network.py
neurodynex3/hopfield_network/pattern_tools.py
neurodynex3/hopfield_network/plot_tools.py
neurodynex3/leaky_integrate_and_fire/LIF.py
neurodynex3/leaky_integrate_and_fire/__init__.py
neurodynex3/neuron_type/__init__.py
neurodynex3/neuron_type/neurons.py
neurodynex3/ojas_rule/__init__.py
neurodynex3/ojas_rule/oja.py
neurodynex3/phase_plane_analysis/__init__.py
neurodynex3/phase_plane_analysis/fitzhugh_nagumo.py
neurodynex3/test/__init__.py
neurodynex3/test/test_AdEx.py
neurodynex3/test/test_HH.py
neurodynex3/test/test_LIF.py
neurodynex3/test/test_LIF_spiking_network.py
neurodynex3/test/test_cable_equation.py
neurodynex3/test/test_decision_making.py
neurodynex3/test/test_exponential_IF.py
neurodynex3/test/test_hopfield.py
neurodynex3/test/test_nagumo.py
neurodynex3/test/test_neuron_type.py
neurodynex3/test/test_oja.py
neurodynex3/test/test_spike_tools.py
neurodynex3/test/test_working_memory.py
neurodynex3/tools/__init__.py
neurodynex3/tools/input_factory.py
neurodynex3/tools/plot_tools.py
neurodynex3/tools/spike_tools.py
neurodynex3/working_memory_network/__init__.py
neurodynex3/working_memory_network/wm_model.py
neurodynex3-1.0.4.dist-info/LICENSE.txt
neurodynex3-1.0.4.dist-info/METADATA
neurodynex3-1.0.4.dist-info/WHEEL
neurodynex3-1.0.4.dist-info/top_level.txt
neurodynex3-1.0.4.dist-info/RECORD
