Metadata-Version: 2.1
Name: neurodynex3
Version: 1.0.4
Summary: Python exercises accompanying the book Neuronal Dynamics by Wulfram Gerstner, Werner M. Kistler, Richard Naud and Liam Paninski.
Home-page: https://github.com/EPFL-LCN/neuronaldynamics-exercises
Download-URL: https://github.com/martinbarry59/neurodynex3/archive/1.0.0.tar.gz
Author: LCN-EPFL
Author-email: martin.barry@epfl.ch
License: GPLv2
Keywords: compneuro,science,teaching,neuroscience,brian
Classifier: License :: OSI Approved :: GNU General Public License v2 (GPLv2)
Classifier: Topic :: Scientific/Engineering :: Medical Science Apps.
Classifier: Programming Language :: Python :: 3
Classifier: Operating System :: OS Independent
Requires-Python: >=3.6
License-File: LICENSE.txt
Requires-Dist: scipy ==1.12.0
Requires-Dist: brian2 ==2.5.4
Requires-Dist: matplotlib ==3.8.3
Requires-Dist: mpmath ==1.3.0
Requires-Dist: setuptools ==69.1.1
Requires-Dist: setuptools-scm ==8.0.4
Requires-Dist: mock ==5.1.0
Requires-Dist: nose ==1.3.7
